Metadata-Version: 1.1
Name: HTMLTestRunner_Python3
Version: 0.8.0
Summary: suite original HTMLTestRunner to python3
Home-page: http://tungwaiyip.info/
Author: tungwaiyip
Author-email: wy@tungwaiyip.info
License: UNKNOWN
Keywords: HTMLTestRunner
Platform: UNKNOWN
Classifier: License :: OSI Approved :: MIT License
Classifier: Programming Language :: Python
Classifier: Intended Audience :: Developers
Classifier: Operating System :: OS Independent
